<?xml version="1.0" ?>
<annotation>
	<folder>images</folder>
	<filename>IMG10653_Label_285.jpg</filename>
	<path>F:\vehicle-detection\images\IMG10653_Label_285.jpg</path>
	<source>
		<database>Unknown</database>
	</source>
	<size>
		<width>490</width>
		<height>320</height>
		<depth>3</depth>
	</size>
	<segmented>0</segmented>
	<object>
		<name>°ÂµÏ-Q5</name>
		<pose>Unspecified</pose>
		<truncated>0</truncated>
		<difficult>0</difficult>
		<bndbox>
			<xmin>96</xmin>
			<ymin>95</ymin>
			<xmax>455</xmax>
			<ymax>258</ymax>
		</bndbox>
	</object>
	<object>
		<name>°ÂµÏ-Q5</name>
		<pose>Unspecified</pose>
		<truncated>0</truncated>
		<difficult>0</difficult>
		<bndbox>
			<xmin>6</xmin>
			<ymin>98</ymin>
			<xmax>130</xmax>
			<ymax>212</ymax>
		</bndbox>
	</object>
</annotation>
