<?xml version="1.0" ?>
<annotation>
	<folder>images</folder>
	<filename>IMG1187_Label_387.jpg</filename>
	<path>F:\vehicle-detection\images\IMG1187_Label_387.jpg</path>
	<source>
		<database>Unknown</database>
	</source>
	<size>
		<width>434</width>
		<height>320</height>
		<depth>3</depth>
	</size>
	<segmented>0</segmented>
	<object>
		<name>ÈÕ²ú-Friend-ME</name>
		<pose>Unspecified</pose>
		<truncated>0</truncated>
		<difficult>0</difficult>
		<bndbox>
			<xmin>33</xmin>
			<ymin>128</ymin>
			<xmax>419</xmax>
			<ymax>306</ymax>
		</bndbox>
	</object>
</annotation>
