<?xml version="1.0" ?>
<annotation>
	<folder>images</folder>
	<filename>IMG1914_Label_649.jpg</filename>
	<path>F:\vehicle-detection\images\IMG1914_Label_649.jpg</path>
	<source>
		<database>Unknown</database>
	</source>
	<size>
		<width>320</width>
		<height>430</height>
		<depth>3</depth>
	</size>
	<segmented>0</segmented>
	<object>
		<name>¡Âƒæ-ÃÏ”ÔSX4</name>
		<pose>Unspecified</pose>
		<truncated>0</truncated>
		<difficult>0</difficult>
		<bndbox>
			<xmin>1</xmin>
			<ymin>53</ymin>
			<xmax>320</xmax>
			<ymax>388</ymax>
		</bndbox>
	</object>
</annotation>
