<?xml version="1.0" ?>
<annotation>
	<folder>images</folder>
	<filename>IMG14103_Label_679.jpg</filename>
	<path>F:/vehicle-detection/images\IMG14103_Label_679.jpg</path>
	<source>
		<database>Unknown</database>
	</source>
	<size>
		<width>432</width>
		<height>320</height>
		<depth>3</depth>
	</size>
	<segmented>0</segmented>
	<object>
		<name>陆风-X8</name>
		<pose>Unspecified</pose>
		<truncated>0</truncated>
		<difficult>0</difficult>
		<bndbox>
			<xmin>408</xmin>
			<ymin>149</ymin>
			<xmax>428</xmax>
			<ymax>207</ymax>
		</bndbox>
	</object>
	<object>
		<name>陆风-X8</name>
		<pose>Unspecified</pose>
		<truncated>0</truncated>
		<difficult>0</difficult>
		<bndbox>
			<xmin>7</xmin>
			<ymin>112</ymin>
			<xmax>119</xmax>
			<ymax>170</ymax>
		</bndbox>
	</object>
	<object>
		<name>陆风-X8</name>
		<pose>Unspecified</pose>
		<truncated>0</truncated>
		<difficult>0</difficult>
		<bndbox>
			<xmin>372</xmin>
			<ymin>146</ymin>
			<xmax>426</xmax>
			<ymax>215</ymax>
		</bndbox>
	</object>
	<object>
		<name>陆风-X8</name>
		<pose>Unspecified</pose>
		<truncated>0</truncated>
		<difficult>0</difficult>
		<bndbox>
			<xmin>54</xmin>
			<ymin>96</ymin>
			<xmax>384</xmax>
			<ymax>256</ymax>
		</bndbox>
	</object>
	<object>
		<name>陆风-X8</name>
		<pose>Unspecified</pose>
		<truncated>0</truncated>
		<difficult>0</difficult>
		<bndbox>
			<xmin>0</xmin>
			<ymin>106</ymin>
			<xmax>116</xmax>
			<ymax>245</ymax>
		</bndbox>
	</object>
</annotation>
