<?xml version="1.0" ?>
<annotation>
	<folder>images</folder>
	<filename>IMG23598_Label_598.jpg</filename>
	<path>F:\vehicle-detection\images\IMG23598_Label_598.jpg</path>
	<source>
		<database>Unknown</database>
	</source>
	<size>
		<width>434</width>
		<height>320</height>
		<depth>3</depth>
	</size>
	<segmented>0</segmented>
	<object>
		<name>Ú©¸è-NSX</name>
		<pose>Unspecified</pose>
		<truncated>0</truncated>
		<difficult>0</difficult>
		<bndbox>
			<xmin>11</xmin>
			<ymin>129</ymin>
			<xmax>416</xmax>
			<ymax>284</ymax>
		</bndbox>
	</object>
</annotation>
