<?xml version="1.0" ?>
<annotation>
	<folder>images</folder>
	<filename>IMG26437_Label_748.jpg</filename>
	<path>F:\vehicle-detection\images\IMG26437_Label_748.jpg</path>
	<source>
		<database>Unknown</database>
	</source>
	<size>
		<width>434</width>
		<height>320</height>
		<depth>3</depth>
	</size>
	<segmented>0</segmented>
	<object>
		<name>À×Åµ-À­¹ÅÄÇ</name>
		<pose>Unspecified</pose>
		<truncated>0</truncated>
		<difficult>0</difficult>
		<bndbox>
			<xmin>84</xmin>
			<ymin>95</ymin>
			<xmax>363</xmax>
			<ymax>300</ymax>
		</bndbox>
	</object>
</annotation>
