<?xml version="1.0" ?>
<annotation>
	<folder>images</folder>
	<filename>IMG2463_Label_656.jpg</filename>
	<path>F:\vehicle-detection\images\IMG2463_Label_656.jpg</path>
	<source>
		<database>Unknown</database>
	</source>
	<size>
		<width>434</width>
		<height>320</height>
		<depth>3</depth>
	</size>
	<segmented>0</segmented>
	<object>
		<name>¡Âƒæ-”Í—‡</name>
		<pose>Unspecified</pose>
		<truncated>0</truncated>
		<difficult>0</difficult>
		<bndbox>
			<xmin>94</xmin>
			<ymin>82</ymin>
			<xmax>337</xmax>
			<ymax>275</ymax>
		</bndbox>
	</object>
</annotation>
