<?xml version="1.0" ?>
<annotation>
	<folder>images</folder>
	<filename>IMG40869_Label_255.jpg</filename>
	<path>images/in/IMG40869_Label_255.jpg</path>
	<source>
		<database>Unknown</database>
	</source>
	<size>
		<width>587</width>
		<height>320</height>
		<depth>3</depth>
	</size>
	<segmented>0</segmented>
	<object>
		<name>±¼³Û-E¼¶AMG</name>
		<pose>Unspecified</pose>
		<truncated>0</truncated>
		<difficult>0</difficult>
		<bndbox>
			<xmin>38</xmin>
			<ymin>79</ymin>
			<xmax>569</xmax>
			<ymax>274</ymax>
		</bndbox>
	</object>
</annotation>
